oregpt/chat_bot.py
oregpt/command.py
oregpt/main.py
oregpt/resources/config.yml
oregpt/stdinout.py
oregpt-0.2.1.dist-info/LICENSE
oregpt-0.2.1.dist-info/METADATA
oregpt-0.2.1.dist-info/WHEEL
oregpt-0.2.1.dist-info/entry_points.txt
oregpt-0.2.1.dist-info/RECORD
