Metadata-Version: 2.1
Name: oregpt
Version: 0.2.1
Summary: A tiny GPT CLI tool
Home-page: https://github.com/shinichi-takayanagi/oregpt
License: MIT
Keywords: gpt-chatbot,gpt-cli,openai-cli
Author: Shinichi Takayanagi
Author-email: shinichi.takayanagi@gmail.com
Requires-Python: >=3.10,<4.0
Classifier: License :: OSI Approved :: MIT License
Classifier: Programming Language :: Python :: 3
Classifier: Programming Language :: Python :: 3.10
Classifier: Programming Language :: Python :: 3.11
Classifier: Programming Language :: Python :: 3.10
Classifier: Programming Language :: Python :: 3.11
Classifier: Topic :: Utilities
Requires-Dist: click (>=8.1.3,<9.0.0)
Requires-Dist: openai (>=0.27.6,<0.28.0)
Requires-Dist: prompt-toolkit (>=3.0.38,<4.0.0)
Requires-Dist: pyyaml (>=6.0,<7.0)
Project-URL: Repository, https://github.com/shinichi-takayanagi/oregpt
